mtsh
