Metadata-Version: 1.1
Name: mtsh
Version: 0.2.0
Summary: multi server ssh interface
Home-page: https://github.com/zdzielinski/mtsh
Author: Zachariah Dzielinski
Author-email: zachdzielinski@gmail.com
License: GNU General Public License v3
Keywords: mtsh
Platform: UNKNOWN
Classifier: Development Status :: 2 - Pre-Alpha
Classifier: Intended Audience :: Developers
Classifier: License :: OSI Approved :: GNU General Public License v3 (GPLv3)
Classifier: Natural Language :: English
Classifier: Programming Language :: Python :: 2
Classifier: Programming Language :: Python :: 2.6
Classifier: Programming Language :: Python :: 2.7
Classifier: Programming Language :: Python :: 3
Classifier: Programming Language :: Python :: 3.3
Classifier: Programming Language :: Python :: 3.4
Classifier: Programming Language :: Python :: 3.5
